{"lastUsed":1707382287579,"path":"C:\/Users\/daw1\/eclipse-workspace","projectCount":21,"recentFiles":[{"path":"\/Listas_2\/src\/act_2","parentWorkspace":"C:\/Users\/daw1\/eclipse-workspace","name":"Agenda.java","lastModified":1706260693305,"locationURI":"file:\/C:\/Users\/daw1\/eclipse-workspace\/Listas_2\/src\/act_2\/Agenda.java"},{"path":"\/Act_1_Excepciones\/src\/act_1","parentWorkspace":"C:\/Users\/daw1\/eclipse-workspace","name":"Act_1.java","lastModified":1707296781859,"locationURI":"file:\/C:\/Users\/daw1\/eclipse-workspace\/Act_1_Excepciones\/src\/act_1\/Act_1.java"},{"path":"\/Act_1_Excepciones\/src\/act_1","parentWorkspace":"C:\/Users\/daw1\/eclipse-workspace","name":"NumeroPositivoException.java","lastModified":1706775397431,"locationURI":"file:\/C:\/Users\/daw1\/eclipse-workspace\/Act_1_Excepciones\/src\/act_1\/NumeroPositivoException.java"},{"path":"\/DawBank\/src\/DawBank","parentWorkspace":"C:\/Users\/daw1\/eclipse-workspace","name":"Tipo.java","lastModified":1707296781700,"locationURI":"file:\/C:\/Users\/daw1\/eclipse-workspace\/DawBank\/src\/DawBank\/Tipo.java"},{"path":"\/Mascotas\/src\/mascotas","parentWorkspace":"C:\/Users\/daw1\/eclipse-workspace","name":"Aves.java","lastModified":1707379616792,"locationURI":"file:\/C:\/Users\/daw1\/eclipse-workspace\/Mascotas\/src\/mascotas\/Aves.java"},{"path":"\/DawBank\/src\/DawBank","parentWorkspace":"C:\/Users\/daw1\/eclipse-workspace","name":"Cliente.java","lastModified":1707299132871,"locationURI":"file:\/C:\/Users\/daw1\/eclipse-workspace\/DawBank\/src\/DawBank\/Cliente.java"},{"path":"\/Mascotas\/src\/mascotas","parentWorkspace":"C:\/Users\/daw1\/eclipse-workspace","name":"Mascotas.java","lastModified":1707290651190,"locationURI":"file:\/C:\/Users\/daw1\/eclipse-workspace\/Mascotas\/src\/mascotas\/Mascotas.java"},{"path":"\/Act_1_Excepciones\/src\/act_1","parentWorkspace":"C:\/Users\/daw1\/eclipse-workspace","name":"EdadException.java","lastModified":1707289715288,"locationURI":"file:\/C:\/Users\/daw1\/eclipse-workspace\/Act_1_Excepciones\/src\/act_1\/EdadException.java"},{"path":"\/Mascotas\/src\/mascotas","parentWorkspace":"C:\/Users\/daw1\/eclipse-workspace","name":"Canario.java","lastModified":1707382287585,"locationURI":"file:\/C:\/Users\/daw1\/eclipse-workspace\/Mascotas\/src\/mascotas\/Canario.java"},{"path":"\/Act_1_Excepciones\/src\/act_1","parentWorkspace":"C:\/Users\/daw1\/eclipse-workspace","name":"NombreLongitudException.java","lastModified":1707289715288,"locationURI":"file:\/C:\/Users\/daw1\/eclipse-workspace\/Act_1_Excepciones\/src\/act_1\/NombreLongitudException.java"},{"path":"\/DawBank\/src\/DawBank","parentWorkspace":"C:\/Users\/daw1\/eclipse-workspace","name":"CuentaBancaria.java","lastModified":1707298649999,"locationURI":"file:\/C:\/Users\/daw1\/eclipse-workspace\/DawBank\/src\/DawBank\/CuentaBancaria.java"},{"path":"\/Act_1_Excepciones\/src\/act_1","parentWorkspace":"C:\/Users\/daw1\/eclipse-workspace","name":"NumeroNegativoException.java","lastModified":1706775397438,"locationURI":"file:\/C:\/Users\/daw1\/eclipse-workspace\/Act_1_Excepciones\/src\/act_1\/NumeroNegativoException.java"},{"path":"\/DawBank\/src\/DawBank","parentWorkspace":"C:\/Users\/daw1\/eclipse-workspace","name":"AvisarHaciendaException.java","lastModified":1707298650004,"locationURI":"file:\/C:\/Users\/daw1\/eclipse-workspace\/DawBank\/src\/DawBank\/AvisarHaciendaException.java"},{"path":"\/Mascotas\/src\/mascotas","parentWorkspace":"C:\/Users\/daw1\/eclipse-workspace","name":"Gato.java","lastModified":1707382287580,"locationURI":"file:\/C:\/Users\/daw1\/eclipse-workspace\/Mascotas\/src\/mascotas\/Gato.java"},{"path":"\/DawBank\/src\/DawBank","parentWorkspace":"C:\/Users\/daw1\/eclipse-workspace","name":"Movimiento.java","lastModified":1707298650015,"locationURI":"file:\/C:\/Users\/daw1\/eclipse-workspace\/DawBank\/src\/DawBank\/Movimiento.java"},{"path":"\/Listas_2\/src\/act_2","parentWorkspace":"C:\/Users\/daw1\/eclipse-workspace","name":"main.java","lastModified":1706260793512,"locationURI":"file:\/C:\/Users\/daw1\/eclipse-workspace\/Listas_2\/src\/act_2\/main.java"},{"path":"\/Listas_2\/src\/act_2","parentWorkspace":"C:\/Users\/daw1\/eclipse-workspace","name":"Contacto.java","lastModified":1706260868537,"locationURI":"file:\/C:\/Users\/daw1\/eclipse-workspace\/Listas_2\/src\/act_2\/Contacto.java"},{"path":"\/DawBank\/src\/DawBank","parentWorkspace":"C:\/Users\/daw1\/eclipse-workspace","name":"Persona.java","lastModified":1707299132994,"locationURI":"file:\/C:\/Users\/daw1\/eclipse-workspace\/DawBank\/src\/DawBank\/Persona.java"},{"path":"\/Act_1_Excepciones\/src\/act_1","parentWorkspace":"C:\/Users\/daw1\/eclipse-workspace","name":"Gato.java","lastModified":1707296781731,"locationURI":"file:\/C:\/Users\/daw1\/eclipse-workspace\/Act_1_Excepciones\/src\/act_1\/Gato.java"},{"path":"\/Actividades","parentWorkspace":"C:\/Users\/daw1\/eclipse-workspace","name":"A1.java","lastModified":1706257464989,"locationURI":"file:\/C:\/Users\/daw1\/eclipse-workspace\/Actividades\/A1.java"},{"path":"\/DawBank\/src\/DawBank","parentWorkspace":"C:\/Users\/daw1\/eclipse-workspace","name":"CuentaException.java","lastModified":1707298650010,"locationURI":"file:\/C:\/Users\/daw1\/eclipse-workspace\/DawBank\/src\/DawBank\/CuentaException.java"},{"path":"\/Mascotas\/src\/mascotas","parentWorkspace":"C:\/Users\/daw1\/eclipse-workspace","name":"Inventario.java","lastModified":1707382287718,"locationURI":"file:\/C:\/Users\/daw1\/eclipse-workspace\/Mascotas\/src\/mascotas\/Inventario.java"},{"path":"\/DawBank\/src\/DawBank","parentWorkspace":"C:\/Users\/daw1\/eclipse-workspace","name":"DawBank.java","lastModified":1707298650142,"locationURI":"file:\/C:\/Users\/daw1\/eclipse-workspace\/DawBank\/src\/DawBank\/DawBank.java"}]}